fastapi_admin_sdk/__init__.py
fastapi_admin_sdk/admin.py
fastapi_admin_sdk/dependencies.py
fastapi_admin_sdk/routes.py
fastapi_admin_sdk/config/__init__.py
fastapi_admin_sdk/config/settings.py
fastapi_admin_sdk/db/__init__.py
fastapi_admin_sdk/db/session_factory.py
fastapi_admin_sdk/db/sqlalchemy_factory.py
fastapi_admin_sdk/forms/__init__.py
fastapi_admin_sdk/forms/base.py
fastapi_admin_sdk/forms/fields.py
fastapi_admin_sdk/resource/__init__.py
fastapi_admin_sdk/resource/base.py
fastapi_admin_sdk/resource/sqlalchemy.py
fastapi_admin_sdk/services/__init__.py
fastapi_admin_sdk/services/admin_service.py
fastapi_admin_sdk-0.1.1.dist-info/METADATA
fastapi_admin_sdk-0.1.1.dist-info/WHEEL
fastapi_admin_sdk-0.1.1.dist-info/licenses/LICENSE
fastapi_admin_sdk-0.1.1.dist-info/RECORD
