Metadata-Version: 2.4
Name: fastapi-admin-sdk
Version: 0.1.1
Summary: A FastAPI admin SDK for building admin interfaces with resource management, permissions, and CRUD operations
Project-URL: Homepage, https://github.com/Ohuru-Tech/fastapi-admin-sdk
Project-URL: Documentation, https://github.com/Ohuru-Tech/fastapi-admin-sdk#readme
Project-URL: Repository, https://github.com/Ohuru-Tech/fastapi-admin-sdk
Project-URL: Issues, https://github.com/Ohuru-Tech/fastapi-admin-sdk/issues
Author-email: amartya-dev <amarkaushik1999@gmail.com>
License: MIT
License-File: LICENSE
Keywords: admin,async,crud,fastapi,rest-api,sdk,sqlalchemy
Classifier: Development Status :: 3 - Alpha
Classifier: Framework :: FastAPI
Classifier: Intended Audience :: Developers
Classifier: License :: OSI Approved :: MIT License
Classifier: Programming Language :: Python :: 3
Classifier: Programming Language :: Python :: 3.11
Classifier: Programming Language :: Python :: 3.12
Classifier: Topic :: Software Development :: Libraries :: Python Modules
Requires-Python: >=3.11
Requires-Dist: aiosqlite>=0.19.0
Requires-Dist: fastapi[standard]>=0.128.0
Requires-Dist: pydantic-settings>=2.0.0
Requires-Dist: pydantic>=2.12.5
Requires-Dist: sqlalchemy[asyncio]>=2.0.45
Provides-Extra: dev
Requires-Dist: build>=1.0.0; extra == 'dev'
Requires-Dist: httpx>=0.24.0; extra == 'dev'
Requires-Dist: pytest-asyncio>=0.21.0; extra == 'dev'
Requires-Dist: pytest-cov>=4.1.0; extra == 'dev'
Requires-Dist: pytest>=7.4.0; extra == 'dev'
